README.md
setup.cfg
setup.py
wacky_envs/__init__.py
wacky_envs/env.py
wacky_envs.egg-info/PKG-INFO
wacky_envs.egg-info/SOURCES.txt
wacky_envs.egg-info/dependency_links.txt
wacky_envs.egg-info/requires.txt
wacky_envs.egg-info/top_level.txt
wacky_envs/actions/__init__.py
wacky_envs/actions/box_actions.py
wacky_envs/actions/discrete_actions.py
wacky_envs/actions/to_action.py
wacky_envs/constraints/__init__.py
wacky_envs/constraints/allocations.py
wacky_envs/constraints/base_float.py
wacky_envs/constraints/base_integer.py
wacky_envs/constraints/conditionals.py
wacky_envs/constraints/constr_float.py
wacky_envs/constraints/constr_integers.py
wacky_envs/constraints/math_equation.py
wacky_envs/constraints/transfers.py
wacky_envs/data_handler/__init__.py
wacky_envs/data_handler/group.py
wacky_envs/data_handler/step_indexing.py
wacky_envs/decisions/__init__.py
wacky_envs/decisions/by_index.py
wacky_envs/distances/__init__.py
wacky_envs/observations/__init__.py
wacky_envs/observations/box_obs.py
wacky_envs/observations/to_obs.py
wacky_envs/step_functions/__init__.py
wacky_envs/step_functions/step_func.py
wacky_envs/step_functions/stepper.py